{
  "original_uri": "https://www.odu.edu/ts/software-services",
  "self": "http://localhost:1208/timemap/json/https://www.odu.edu/ts/software-services",
  "mementos": {
    "list": [
      {
        "datetime": "2021-11-05T09:13:22Z",
        "uri": "https://arquivo.pt/wayback/20211105091322mp_/https://odu.edu/ts/software-services"
      },
      {
        "datetime": "2021-11-11T03:36:16Z",
        "uri": "https://arquivo.pt/wayback/20211111033616mp_/http://www.odu.edu/ts/software-services"
      },
      {
        "datetime": "2022-08-27T20:16:06Z",
        "uri": "https://arquivo.pt/wayback/20220827201606mp_/https://www.odu.edu/ts/software-services"
      }
    ],
    "first": {
      "datetime": "2021-11-05T09:13:22Z",
      "uri": "https://arquivo.pt/wayback/20211105091322mp_/https://odu.edu/ts/software-services"
    },
    "last": {
      "datetime": "2022-08-27T20:16:06Z",
      "uri": "https://arquivo.pt/wayback/20220827201606mp_/https://www.odu.edu/ts/software-services"
    }
  },
  "timemap_uri": {
    "link_format": "http://localhost:1208/timemap/link/https://www.odu.edu/ts/software-services",
    "json_format": "http://localhost:1208/timemap/json/https://www.odu.edu/ts/software-services",
    "cdxj_format": "http://localhost:1208/timemap/cdxj/https://www.odu.edu/ts/software-services"
  },
  "timegate_uri": "http://localhost:1208/timegate/https://www.odu.edu/ts/software-services"
}
